README.rst
setup.py
Fondue.egg-info/PKG-INFO
Fondue.egg-info/SOURCES.txt
Fondue.egg-info/dependency_links.txt
Fondue.egg-info/entry_points.txt
Fondue.egg-info/requires.txt
Fondue.egg-info/top_level.txt
fondue/__init__.py
fondue/__main__.py
fondue/api.py
fondue/config.py
fondue/fond_socket.py
fondue/parser.c
fondue/protocol.c
fondue/stun.py
fondue/tap.py
fondue/tcp_client.py
fondue/tcp_serv.py
fondue/udp_data.py