Metadata-Version: 1.2
Name: Fondue
Version: 0.11.2
Summary: Connect peers on a virtual LAN, punching through network barriers.
Home-page: UNKNOWN
Author: Ariel Antonitis
Author-email: arant@mit.edu
License: MIT
Platform: UNKNOWN
Classifier: License :: OSI Approved :: MIT License
Classifier: Development Status :: 2 - Pre-Alpha
Classifier: Topic :: System :: Networking
Classifier: Topic :: Internet
Requires-Python: >=3.5
